auto_trace_analyzer/__init__.py
auto_trace_analyzer/analyzer.py
auto_trace_analyzer/cli.py
auto_trace_analyzer/runner.py
auto_trace_analyzer-0.1.1.dist-info/METADATA
auto_trace_analyzer-0.1.1.dist-info/WHEEL
auto_trace_analyzer-0.1.1.dist-info/entry_points.txt
auto_trace_analyzer-0.1.1.dist-info/top_level.txt
auto_trace_analyzer-0.1.1.dist-info/RECORD
