Metadata-Version: 2.1
Name: auto-trace-analyzer
Version: 0.1.1
Summary: A lightweight automated engine for traceback analysis and explanation.
License: GPL-3.0
Project-URL: Homepage, https://github.com/EngineNodeX/auto-trace-analyzer
Requires-Python: >=3.8
Requires-Dist: openai >=1.0.0
Requires-Dist: click >=8.0
